lcdmanager-0.4.0.dist-info/WHEEL
lcdmanager-0.4.0.dist-info/RECORD
lcdmanager-0.4.0.dist-info/METADATA
lcdmanager-0.4.0.dist-info/DESCRIPTION.rst
lcdmanager-0.4.0.dist-info/metadata.json
lcdmanager-0.4.0.dist-info/top_level.txt
lcdmanager/__init__.py
lcdmanager/display.py
lcdmanager/manager.py
lcdmanager/abstract/__init__.py
lcdmanager/abstract/widget.py
lcdmanager/abstract/event/__init__.py
lcdmanager/abstract/event/focus.py
lcdmanager/abstract/event/action.py
lcdmanager/demos/__init__.py
lcdmanager/demos/label.py
lcdmanager/demos/display.py
lcdmanager/demos/remote_read.py
lcdmanager/demos/canvas.py
lcdmanager/demos/pane.py
lcdmanager/remote/__init__.py
lcdmanager/remote/server.py
lcdmanager/widget/__init__.py
lcdmanager/widget/button.py
lcdmanager/widget/label.py
lcdmanager/widget/canvas.py
lcdmanager/widget/pane.py
